setup.py
dg_graph/__init__.py
dg_graph/exceptions.py
dg_graph/graph.py
dg_graph/link.py
dg_graph/result.py
dg_graph.egg-info/PKG-INFO
dg_graph.egg-info/SOURCES.txt
dg_graph.egg-info/dependency_links.txt
dg_graph.egg-info/requires.txt
dg_graph.egg-info/top_level.txt