Metadata-Version: 1.0
Name: dg-graph
Version: 0.0.10
Summary: dg_graph.
Home-page: https://bitbucket.org/serviciosveca/dg_graph
Author: Servicios VECA
Author-email: 1josegomezr@gmail.com
License: Apache Software License
Keywords: graph database grafos
Platform: any
